__init__.py
spectraltools/__init__.py
spectraltools/spectraldense.py
spectraltools/spectralprune.py
spectraltools/spectralprune_experimental.py
spectraltools-1.2.0.dist-info/LICENSE
spectraltools-1.2.0.dist-info/METADATA
spectraltools-1.2.0.dist-info/WHEEL
spectraltools-1.2.0.dist-info/top_level.txt
spectraltools-1.2.0.dist-info/RECORD
