Metadata-Version: 2.1
Name: spectraltools
Version: 1.2.0
Summary: Tools for train and prune in the dual space a fully connected layer.
Home-page: https://github.com/pypa/sampleproject
Author: Lorenzo Giambagli
Project-URL: Bug Tracker, https://github.com/pypa/sampleproject/issues
Classifier: Programming Language :: Python :: 3.10
Classifier: License :: OSI Approved :: MIT License
Classifier: Operating System :: OS Independent
Requires-Python: >=3.7
License-File: LICENSE
